astropy_iers_data/__init__.py
astropy_iers_data/_version.py
astropy_iers_data/data/Leap_Second.dat
astropy_iers_data/data/README.rst
astropy_iers_data/data/ReadMe.eopc04
astropy_iers_data/data/ReadMe.finals2000A
astropy_iers_data/data/eopc04.1962-now
astropy_iers_data/data/finals2000A.all
astropy_iers_data/tests/__init__.py
astropy_iers_data-0.2025.12.22.0.40.30.dist-info/METADATA
astropy_iers_data-0.2025.12.22.0.40.30.dist-info/WHEEL
astropy_iers_data-0.2025.12.22.0.40.30.dist-info/licenses/LICENSE.rst
astropy_iers_data-0.2025.12.22.0.40.30.dist-info/RECORD
