Metadata-Version: 2.4
Name: astropy-iers-data
Version: 0.2025.12.22.0.40.30
Summary: IERS Earth Rotation and Leap Second tables for the astropy core package
Project-URL: repository, https://github.com/astropy/astropy-iers-data
Project-URL: documentation, https://github.com/astropy/astropy-iers-data/blob/main/README.rst
Author-email: Astropy Developers <astropy.team@gmail.com>
License-Expression: BSD-3-Clause
License-File: LICENSE.rst
Keywords: IERS,astropy,data
Classifier: Intended Audience :: Developers
Classifier: Intended Audience :: Science/Research
Classifier: Operating System :: OS Independent
Classifier: Programming Language :: Python :: 3
Requires-Python: >=3.8
Provides-Extra: docs
Requires-Dist: pytest; extra == 'docs'
Provides-Extra: test
Requires-Dist: hypothesis; extra == 'test'
Requires-Dist: pytest; extra == 'test'
Requires-Dist: pytest-remotedata; extra == 'test'
